mmi/__init__.py
mmi/cli.py
mmi/curl.py
mmi/mmi_client.py
mmi/runner.py
mmi/runner_legacy.py
mmi/tracker.py
mmi/tracker_client.py
mmi/tracker_views.py
mmi-0.7.0.dist-info/DESCRIPTION.rst
mmi-0.7.0.dist-info/METADATA
mmi-0.7.0.dist-info/RECORD
mmi-0.7.0.dist-info/WHEEL
mmi-0.7.0.dist-info/entry_points.txt
mmi-0.7.0.dist-info/metadata.json
mmi-0.7.0.dist-info/top_level.txt
