Metadata-Version: 2.0
Name: mmi
Version: 0.7.0
Summary: Model Message Interface
Home-page: http://github.com/openearth/python-mmi
Author: Fedor Baart
Author-email: fedor.baart@deltares.nl
License: GPLv3+
Keywords: array messages model
Platform: UNKNOWN
Classifier: Development Status :: 4 - Beta
Classifier: Intended Audience :: Science/Research
Classifier: Intended Audience :: Developers
Classifier: Topic :: Scientific/Engineering
Classifier: Topic :: System :: Distributed Computing
Classifier: License :: OSI Approved :: GNU General Public License v3 (GPLv3)
Classifier: Programming Language :: Python :: 3
Classifier: Programming Language :: Python :: 3.5
Classifier: Programming Language :: Python :: 3.6
Requires-Dist: numpy
Requires-Dist: pyzmq
Requires-Dist: bmi-python
Requires-Dist: tornado
Requires-Dist: requests
Requires-Dist: six
Requires-Dist: shapely
Requires-Dist: click
